GenZBot/__init__.py
GenZBot/chatbot.py
GenZBot/utils_list/__init__.py
GenZBot/utils_list/AIModels/__init__.py
GenZBot/utils_list/AIModels/response.py
GenZBot/utils_list/Images_list/galaxy_img.png
GenZBot/utils_list/backend/__init__.py
GenZBot/utils_list/backend/flask_app.py
GenZBot/utils_list/templates_list/__init__.py
GenZBot/utils_list/templates_list/design1/__init__.py
GenZBot/utils_list/templates_list/design1/index.py
GenZBot/utils_list/templates_list/design1/script.py
GenZBot/utils_list/templates_list/design1/style.py
GenZBot/utils_list/templates_list/design2/__init__.py
GenZBot/utils_list/templates_list/design2/index.py
GenZBot/utils_list/templates_list/design2/script.py
GenZBot/utils_list/templates_list/design2/style.py
GenZBot-0.8.dist-info/License.txt
GenZBot-0.8.dist-info/METADATA
GenZBot-0.8.dist-info/WHEEL
GenZBot-0.8.dist-info/top_level.txt
GenZBot-0.8.dist-info/RECORD
