Metadata-Version: 2.1
Name: GenZBot
Version: 0.8
Summary: GenZBot is a beginner-friendly Python package designed to provide hands-on experience in building AI chatbots from scratch. With support for multiple LLMs and customizable options for behavior and design, it simplifies chatbot development while introducing essential concepts for GenAI projects.
Author: Anurupa Karmakar and Vishnu Kumar
Author-email: anurupakarmakar.dgp18@gmail.com
Maintainer: Anurupa Karmakar
Maintainer-email: anurupakarmakar.dgp18@gmail.com
Classifier: Programming Language :: Python :: 3
Classifier: License :: OSI Approved :: BSD License
Classifier: Operating System :: OS Independent
License-File: License.txt
